xontrib/powerline3.py
xontrib_powerline3/__init__.py
xontrib_powerline3/colors.py
xontrib_powerline3/fields.py
xontrib_powerline3/processor.py
xontrib_powerline3/shell.py
xontrib_powerline3-0.3.17.dist-info/LICENSE
xontrib_powerline3-0.3.17.dist-info/WHEEL
xontrib_powerline3-0.3.17.dist-info/METADATA
xontrib_powerline3-0.3.17.dist-info/RECORD
