Metadata-Version: 2.1
Name: xontrib-powerline3
Version: 0.3.17
Summary: Yet another powerline theme for xonsh with async prompt support.
Home-page: https://github.com/jnoortheen/xontrib-powerline3
License: MIT
Keywords: xontrib,xonsh
Author: Noortheen Raja NJ
Author-email: jnoortheen@gmail.com
Requires-Python: >=3.8
Classifier: Intended Audience :: Developers
Classifier: License :: OSI Approved :: MIT License
Classifier: Natural Language :: English
Classifier: Operating System :: OS Independent
Classifier: Programming Language :: Python
Classifier: Programming Language :: Python :: 3
Classifier: Programming Language :: Python :: 3.10
Classifier: Programming Language :: Python :: 3.8
Classifier: Programming Language :: Python :: 3.9
Classifier: Topic :: System :: Shells
Classifier: Topic :: System :: System Shells
Classifier: Topic :: Terminals
Requires-Dist: tomlkit
Requires-Dist: xonsh (>=0.12)
Project-URL: Code, https://github.com/jnoortheen/xontrib-powerline3
Project-URL: Documentation, https://github.com/jnoortheen/xontrib-powerline3/blob/master/README.md
Project-URL: Issue tracker, https://github.com/jnoortheen/xontrib-powerline3/issues
Project-URL: Repository, https://github.com/jnoortheen/xontrib-powerline3
